flatten_dict/__init__.py
flatten_dict/flatten_dict.py
flatten_dict/reducer.py
flatten_dict/splitter.py
flatten_dict/tests/flatten_dict_test.py
flatten_dict-0.2.0.dist-info/LICENSE
flatten_dict-0.2.0.dist-info/WHEEL
flatten_dict-0.2.0.dist-info/METADATA
flatten_dict-0.2.0.dist-info/RECORD
