Metadata-Version: 2.1
Name: flatten-dict
Version: 0.2.0
Summary: A flexible utility for flattening and unflattening dict-like objects in Python.
Home-page: https://github.com/ianlini/flatten-dict
License: MIT
Author: Ian Lin
Author-email: you@example.com
Requires-Python: >=2.7, !=3.0.*, !=3.1.*, !=3.2.*, !=3.3.*, !=3.4.*
Classifier: License :: OSI Approved :: MIT License
Classifier: Programming Language :: Python :: 2
Classifier: Programming Language :: Python :: 2.7
Classifier: Programming Language :: Python :: 3
Classifier: Programming Language :: Python :: 3.5
Classifier: Programming Language :: Python :: 3.6
Classifier: Programming Language :: Python :: 3.7
Classifier: Topic :: Utilities
Requires-Dist: pathlib2 (>=2.3,<3.0)
Requires-Dist: six (>=1.12,<2.0)
Project-URL: Repository, https://github.com/ianlini/flatten-dict
